vigimeteo_cli/__init__.py
vigimeteo_cli/cli.py
vigimeteo_cli-0.5.0.dist-info/METADATA
vigimeteo_cli-0.5.0.dist-info/RECORD
vigimeteo_cli-0.5.0.dist-info/WHEEL
vigimeteo_cli-0.5.0.dist-info/entry_points.txt
vigimeteo_cli-0.5.0.dist-info/top_level.txt
