Metadata-Version: 2.1
Name: vigimeteo-cli
Version: 0.5.0
Summary: Get current French West Indies weather awareness level (Vigilance Meteo)
Home-page: https://work.ipeos.com/gitlab/vigimeteo/vigimeteo-cli
Author: Olivier Watte - IPEOS
Author-email: owatte@ipeos.com
License: UNKNOWN
Platform: UNKNOWN
Classifier: Programming Language :: Python
Classifier: Environment :: Console
Classifier: Development Status :: 5 - Production/Stable
Classifier: Intended Audience :: Science/Research
Classifier: License :: OSI Approved :: GNU General Public License v3 or later (GPLv3+)
Classifier: Natural Language :: English
Classifier: Operating System :: OS Independent
Classifier: Programming Language :: Python :: 3.5
Classifier: Topic :: Scientific/Engineering :: Information Analysis
Requires-Dist: certifi (==2018.4.16)
Requires-Dist: chardet (==3.0.4)
Requires-Dist: docopt (==0.6.2)
Requires-Dist: fake-useragent (==0.1.10)
Requires-Dist: idna (==2.7)
Requires-Dist: pdfminer.six (==20170720)
Requires-Dist: pycryptodome (==3.6.3)
Requires-Dist: requests (==2.19.1)
Requires-Dist: six (==1.11.0)
Requires-Dist: urllib3 (==1.23)
